jax_progress/__init__.py
jax_progress/progress_meter.py
jax_progress/unshard.py
jax_progress/unvmap.py
jax_progress-0.1.0.dist-info/METADATA
jax_progress-0.1.0.dist-info/WHEEL
jax_progress-0.1.0.dist-info/top_level.txt
jax_progress-0.1.0.dist-info/RECORD
