Metadata-Version: 2.4
Name: jax_progress
Version: 0.1.0
Summary: Progress meters for JAX loops and scans
Author: Wassim Kabalan
Keywords: jax,progress,tqdm
Classifier: Development Status :: 3 - Alpha
Classifier: Intended Audience :: Developers
Classifier: License :: OSI Approved :: MIT License
Classifier: Programming Language :: Python :: 3
Requires-Python: >=3.10
Requires-Dist: jax
Requires-Dist: tqdm
Requires-Dist: jaxtyping
Requires-Dist: equinox>=0.13.2
Requires-Dist: numpy
Provides-Extra: test
Requires-Dist: pytest; extra == "test"
Requires-Dist: pytest-cov; extra == "test"
Requires-Dist: chex; extra == "test"
